weatherlink2pg/__init__.py
weatherlink2pg/helpers.py
weatherlink2pg/main.py
weatherlink2pg-1.0.1.dist-info/METADATA
weatherlink2pg-1.0.1.dist-info/WHEEL
weatherlink2pg-1.0.1.dist-info/entry_points.txt
weatherlink2pg-1.0.1.dist-info/RECORD
